PyColor/__init__.py
PyColor/pycolor.py
PyColorator-0.1.2.dist-info/LICENSE
PyColorator-0.1.2.dist-info/METADATA
PyColorator-0.1.2.dist-info/WHEEL
PyColorator-0.1.2.dist-info/top_level.txt
PyColorator-0.1.2.dist-info/RECORD
