Metadata-Version: 2.1
Name: PyColorator
Version: 0.1.2
Summary: A lightweight python library to easily colorate text
Home-page: https://github.com/borgox/PyColorate
Author: borgox
Author-email: 
Classifier: Programming Language :: Python :: 3
Classifier: License :: OSI Approved :: MIT License
Classifier: Operating System :: OS Independent
Requires-Python: >=3.6
License-File: LICENSE
